{
  "item-states": [
    {
      "folded": false,
      "id": "f7ObWdM11M/ofIexJdAJGX"
    },
    {
      "folded": false,
      "id": "70KN97nPtMiL6GhcIYSXU8"
    },
    {
      "folded": false,
      "id": "16JmVyqZhAnq3qTyUCbsZm"
    },
    {
      "folded": false,
      "id": "72N5YBlUVHfblNbjtH5hni"
    },
    {
      "folded": false,
      "id": "e6DsKB/cxKfYdZQYp0jhKD"
    },
    {
      "folded": false,
      "id": "58UE+f3p5G/YCXqaBqX+vP"
    },
    {
      "folded": false,
      "id": "bbPMzwhpxJnKtpuFsZCxnF"
    },
    {
      "folded": false,
      "id": "5bQYwhf8NOz5HSjsuabMu3"
    },
    {
      "folded": false,
      "id": "e9oBpWK9dHEqq794eucicY"
    },
    {
      "folded": false,
      "id": "08YVM0Eq1INYGSLZfqplQG"
    },
    {
      "folded": false,
      "id": "efI1AAQ1BF8oTLCu4jbRY/"
    },
    {
      "folded": false,
      "id": "caGHNzuotIM4Lrf1bki54B"
    },
    {
      "folded": false,
      "id": "57oT0PGDhLnKfIA/qVnpRi"
    },
    {
      "folded": false,
      "id": "6et/ex/stDz4sYWvaN+dwp"
    },
    {
      "folded": false,
      "id": "cdGt2bYXtDC5MXQeLbzYFm"
    },
    {
      "folded": false,
      "id": "71iCb2W/VF2aHjcT+rHjkz"
    },
    {
      "folded": false,
      "id": "23c0NpXOxDFKicGWxJ6VEJ"
    },
    {
      "folded": false,
      "id": "0akutAl4JJ2YUb/ihCirl5"
    },
    {
      "folded": false,
      "id": "5dR56uA+BApr41SUo03877"
    },
    {
      "folded": false,
      "id": "33Q35uT2VIsYonMPatZyN6"
    },
    {
      "folded": false,
      "id": "38IKyOsC9Kn4O4uf+YOxB2"
    },
    {
      "folded": false,
      "id": "baKu076YNE+ZMBF5rnpY0k"
    },
    {
      "folded": true,
      "id": "93BnDy6npNlYyJBcRLOIAI"
    },
    {
      "folded": false,
      "id": "71Ui1bsF5Jqpr8Zln38pNI"
    },
    {
      "folded": false,
      "id": "31vYosGKhEhrtvj8vFN/v4"
    },
    {
      "folded": true,
      "id": "950/WmmHtNvalZFABT3zeI"
    },
    {
      "folded": false,
      "id": "561r6I5uNCr6aPoMEiSMUQ"
    },
    {
      "folded": false,
      "id": "1fePs9QXNOwZkkj/ead35M"
    },
    {
      "folded": false,
      "id": "f2LqpRBZpH8aCJmpFj7e/v"
    },
    {
      "folded": false,
      "id": "7byuM8G4FGr6oZq8BxBRTw"
    },
    {
      "folded": false,
      "id": "2aICEISQlJJqP93eaOYxKX"
    },
    {
      "folded": false,
      "id": "d7P10KfVJDCJNNktPx4K8Z"
    },
    {
      "folded": false,
      "id": "70N8YY0v1IhKWGuo/lFlTq"
    },
    {
      "folded": false,
      "id": "bcjHGISBxPp44Fx62SCgfR"
    },
    {
      "folded": false,
      "id": "earXrVmBpIEJPF6g7tvS0E"
    },
    {
      "folded": true,
      "id": "7d8umWPn5OQblxrYJAtSU1"
    },
    {
      "folded": false,
      "id": "528Y/DmmtJIqRhd3TB5DJa"
    },
    {
      "folded": false,
      "id": "b1qveItUZDAJN94V6yBTOg"
    },
    {
      "folded": false,
      "id": "f7INgL1HlBqp9tZoryKCDv"
    },
    {
      "folded": false,
      "id": "41jJw0SPBKS6t5rKNq+oHv"
    },
    {
      "folded": false,
      "id": "d9RVt+UTdJw4IEZytjy8oi"
    },
    {
      "folded": true,
      "id": "45jx9Pm6pB/L7B8RvK7kcz"
    },
    {
      "folded": false,
      "id": "32lwnMXhVF/pPuirnuE5bg"
    },
    {
      "folded": false,
      "id": "81TzIeTgpH77fxLQmSwPK8"
    },
    {
      "folded": false,
      "id": "28ouwP55tCU5QIRlZkfQRP"
    },
    {
      "folded": false,
      "id": "c12tPT7VJB1bYGt9ljTKPu"
    },
    {
      "folded": false,
      "id": "3eJifs0MREE4mgRZ51s+bd"
    },
    {
      "folded": false,
      "id": "c2QREB9SJKk5OKvdCWWtjb"
    },
    {
      "folded": false,
      "id": "89ciwMA7JLBaCMuKhXK5LQ"
    },
    {
      "folded": false,
      "id": "1bSKNXe6JKt5tiz+fki4nR"
    },
    {
      "folded": false,
      "id": "0eCL7WaLRGuaQHumCuNd2U"
    },
    {
      "folded": false,
      "id": "a3hrZoNBZMsJxX/uv3MVDs"
    },
    {
      "folded": false,
      "id": "95aSu6hvRAVaddbOYDJ/8Z"
    },
    {
      "folded": false,
      "id": "669R1DfRRCbIRQYQX3DP5X"
    },
    {
      "folded": false,
      "id": "d04aG186RK3ZCOMCxGKvzS"
    },
    {
      "folded": false,
      "id": "744Rd4DQJMx6cY6tpqQXVv"
    },
    {
      "folded": false,
      "id": "b81MX/l2ZJwr4mGjTfhQXT"
    },
    {
      "folded": false,
      "id": "150UM7kulKH6/F2wUatY4b"
    },
    {
      "folded": true,
      "id": "94Rvb/lMNPVJKNHjHALV9m"
    },
    {
      "folded": false,
      "id": "4cZDvNOLdEv72hQ/0ZkSwU"
    },
    {
      "folded": false,
      "id": "d9bgPS3R1N9bDMN7q69C2n"
    },
    {
      "folded": false,
      "id": "62WmdguD5LOqJPdwJpUQvp"
    },
    {
      "folded": false,
      "id": "65vubnTdpL8qDlWEwKnEMN"
    },
    {
      "folded": false,
      "id": "09/dZmsylMtoY1eG1AmyuP"
    },
    {
      "folded": false,
      "id": "e8ZWobs6lGRqSLpgyXhKP0"
    },
    {
      "folded": false,
      "id": "c9W5XokoZAIrk98ZZNC5Rh"
    },
    {
      "folded": false,
      "id": "20q8/e2OhAdZCDRaZOO1yK"
    },
    {
      "folded": false,
      "id": "60gMocSg5CzpbIT2ZfqFls"
    },
    {
      "folded": false,
      "id": "eb0T0X++dC4rgXWzK2Lvsp"
    },
    {
      "folded": false,
      "id": "a3E5owf29CR7AirK4/Fi85"
    },
    {
      "folded": false,
      "id": "a4CRsApqVHKau24X4M1agh"
    },
    {
      "folded": false,
      "id": "50zA5pAXhBB6Gd0ycRKF58"
    },
    {
      "folded": false,
      "id": "86l8IuT+hMB5vEwliMW79f"
    },
    {
      "folded": false,
      "id": "83rZGp3vdIsJE/LoP0MeKp"
    },
    {
      "folded": true,
      "id": "a84motADdL+L9w3UhTmmUQ"
    },
    {
      "folded": false,
      "id": "achwFIbwtGXoPqWmxgR8YX"
    },
    {
      "folded": false,
      "id": "88eE7tlJ9KsKtDgNrZXKvv"
    },
    {
      "folded": false,
      "id": "29+kBXAC5BLLQ6/HiDoR9a"
    },
    {
      "folded": false,
      "id": "feru+8lEJFwavIB9WSeuPx"
    },
    {
      "folded": false,
      "id": "16A60BxrdJRYhiwwJ3CtZC"
    },
    {
      "folded": false,
      "id": "dcu2XO3MNFO4k8KzFhdHhG"
    },
    {
      "folded": false,
      "id": "ae5b8A5ANDJLY+2BcRKWmm"
    },
    {
      "folded": false,
      "id": "2fxrkgtwZJfYe6RK7K2ac2"
    },
    {
      "folded": false,
      "id": "d8DXeDeVtAN5A1iR+xsmED"
    },
    {
      "folded": false,
      "id": "48bDsWnBJFIKNZUIEjEJF4"
    },
    {
      "folded": false,
      "id": "1fN6uyen9OgpBi0ZayzGZA"
    },
    {
      "folded": false,
      "id": "0aSonQnB1G9Z4H3URhaKuX"
    },
    {
      "folded": false,
      "id": "b4RoK664RM6KgIH/7MpqZq"
    },
    {
      "folded": false,
      "id": "6drNLLFy1DOqb196LQLFGN"
    },
    {
      "folded": true,
      "id": "7cBIhDmDBML6T8KKPBZqQI"
    },
    {
      "folded": false,
      "id": "80xapxhLRN8L9GLE/uKmIs"
    },
    {
      "folded": false,
      "id": "881CxdpphFtJm6qD2d6rYa"
    },
    {
      "folded": false,
      "id": "0eGw+sMCNI6YntMOGbKVBy"
    },
    {
      "folded": false,
      "id": "33Y3grXelGa6naLuqTQwdM"
    },
    {
      "folded": false,
      "id": "6fWS6teyJBQJfXBJzsb8mh"
    },
    {
      "folded": false,
      "id": "cajRajS1RPGoWHdQ7UrZz3"
    },
    {
      "folded": false,
      "id": "aedlYGcRlNQJSACCo4Zx7P"
    },
    {
      "folded": false,
      "id": "1fuXnfTBlMCY5sniXjY6io"
    },
    {
      "folded": false,
      "id": "88NLbAeU1BfrRYOljCLmOO"
    },
    {
      "folded": false,
      "id": "86mI+E5itGa55wfr+KTQmO"
    },
    {
      "folded": false,
      "id": "78wP/Nj7NMT6Y8CzVnRhvL"
    },
    {
      "folded": false,
      "id": "1c+Z6c0plM7IEQISp42SxU"
    },
    {
      "folded": false,
      "id": "9bGZ2Lj2ZBNKtqUSsZni7x"
    },
    {
      "folded": false,
      "id": "9eRhRVQFxIToyqVDRj4cRp"
    },
    {
      "folded": false,
      "id": "7affBcFOJFt7VPPGuGLrkF"
    },
    {
      "folded": false,
      "id": "f57N9ujeRHpauu/uo/CmxY"
    },
    {
      "folded": false,
      "id": "e7tbpCATZIs5tviw5/SfKW"
    },
    {
      "folded": false,
      "id": "f8s5orUGVGsLLLkunAcU/n"
    },
    {
      "folded": false,
      "id": "e8mswcr1ZKyryhGsFuWnXS"
    },
    {
      "folded": false,
      "id": "1aZFd3IZVNNqvJYR66FUkg"
    },
    {
      "folded": false,
      "id": "e6u3PoRYtEqKeIBTl++qGx"
    },
    {
      "folded": false,
      "id": "24nq8JKfBCgJk0cnOPJPOk"
    },
    {
      "folded": false,
      "id": "32LQ+b1gpO/7k9GbGwJIM1"
    },
    {
      "folded": false,
      "id": "d9ARVE3n5CWbc6YHPp2YVY"
    },
    {
      "folded": false,
      "id": "14db9qV1VJBKVTzr51Nm8C"
    },
    {
      "folded": true,
      "id": "59V48Axb9Eq7kHZX2BGfdA"
    },
    {
      "folded": false,
      "id": "557eBVpKNIpbZLsjzGkbKN"
    },
    {
      "folded": false,
      "id": "73rWf8pv1IEYus7JnurwoJ"
    },
    {
      "folded": false,
      "id": "87zdsZdFdHH5uP9aY3uGYS"
    },
    {
      "folded": false,
      "id": "24HFjWmFZN/pHhbY1LhhGs"
    },
    {
      "folded": false,
      "id": "96w2lCOLZCKqOpNzY+Ox5p"
    },
    {
      "folded": true,
      "id": "72vR3/Nx5LuJrMvvRfGTcU"
    },
    {
      "folded": false,
      "id": "ceoneWiQNLtp9n3dnSHQVq"
    },
    {
      "folded": false,
      "id": "a50HSfKDhFqYRBvJW4o4ha"
    },
    {
      "folded": false,
      "id": "08T7IvGAVHj5sniiAEt/5g"
    },
    {
      "folded": false,
      "id": "3347s2H0hJwJFcbbZkdDgC"
    },
    {
      "folded": false,
      "id": "c5ZB9n0sFACoK7qLzzmrYc"
    },
    {
      "folded": true,
      "id": "2d3sU5wrREmpunTaGLzHqV"
    },
    {
      "folded": false,
      "id": "f0LJbf019JIKh1RNeWn9NH"
    },
    {
      "folded": false,
      "id": "f7SBbxcRVEKpif00swLsOv"
    }
  ]
}